[
  {
    "id": "74a30a90-7b94-454d-8d99-9376cf3cdf4e",
    "runId": "2026-04-25T11-11-43-961Z",
    "implId": "graphql-js-17",
    "testCaseId": "16b4f4d2/68ac87dd/08c2bc4a",
    "status": "excluded",
    "actual": {
      "errors": [
        {
          "message": "Argument \"@defer(label:)\" must be a static string.",
          "locations": [
            {
              "line": 12,
              "column": 17
            }
          ]
        }
      ]
    }
  },
  {
    "id": "481f3a1e-e4b5-41a4-82b2-e3201b58a717",
    "runId": "2026-04-25T11-11-43-961Z",
    "implId": "graphql-js-17",
    "testCaseId": "3369ca5b/ca3604cb/3bf58b42",
    "status": "excluded",
    "actual": {
      "errors": [
        {
          "message": "Argument \"@defer(label:)\" must be a static string.",
          "locations": [
            {
              "line": 2,
              "column": 17
            }
          ]
        }
      ]
    }
  },
  {
    "id": "21cb01e1-871c-4f83-884b-19d7574f7d2b",
    "runId": "2026-04-25T11-11-43-961Z",
    "implId": "graphql-js-17",
    "testCaseId": "3369ca5b/ca3604cb/5227c73d",
    "status": "excluded",
    "actual": {
      "errors": [
        {
          "message": "Argument \"@defer(label:)\" must be a static string.",
          "locations": [
            {
              "line": 2,
              "column": 17
            }
          ]
        }
      ]
    }
  },
  {
    "id": "37fc4673-391a-429c-8320-27cd7bb41642",
    "runId": "2026-04-25T11-11-43-961Z",
    "implId": "graphql-js-17",
    "testCaseId": "587ef7ad/3f6a8118/44136fa3",
    "status": "excluded",
    "actual": {
      "errors": [
        {
          "message": "Argument \"@defer(label:)\" must be a static string.",
          "locations": [
            {
              "line": 2,
              "column": 25
            }
          ]
        }
      ]
    }
  },
  {
    "id": "3b102f85-827a-4085-8654-04ac3a1d31b7",
    "runId": "2026-04-25T11-11-43-961Z",
    "implId": "graphql-js-17",
    "testCaseId": "9c43f4e7/fc0a4ccc/44136fa3",
    "status": "excluded",
    "actual": {
      "errors": [
        {
          "message": "Argument \"@defer(label:)\" must be a static string.",
          "locations": [
            {
              "line": 12,
              "column": 26
            }
          ]
        }
      ]
    }
  },
  {
    "id": "7cb78f07-c9db-439b-8247-eeeacd2815f5",
    "runId": "2026-04-25T11-11-43-961Z",
    "implId": "graphql-js-17",
    "testCaseId": "e0b58892/f6bb3c42/17f9a949",
    "status": "excluded",
    "actual": {
      "errors": [
        {
          "message": "Argument \"@defer(label:)\" must be a static string.",
          "locations": [
            {
              "line": 6,
              "column": 18
            }
          ]
        }
      ]
    }
  },
  {
    "id": "fa6b6a9c-43b0-4616-8b45-61d56c333dd4",
    "runId": "2026-04-25T11-11-43-961Z",
    "implId": "graphql-js-17",
    "testCaseId": "e0b58892/f6bb3c42/44136fa3",
    "status": "excluded",
    "actual": {
      "errors": [
        {
          "message": "Argument \"@defer(label:)\" must be a static string.",
          "locations": [
            {
              "line": 6,
              "column": 18
            }
          ]
        }
      ]
    }
  },
  {
    "id": "552541ad-2939-409b-8862-340c17443c0a",
    "runId": "2026-04-25T11-11-43-961Z",
    "implId": "graphql-js-17",
    "testCaseId": "e0b58892/f6bb3c42/c6bb98b0",
    "status": "excluded",
    "actual": {
      "errors": [
        {
          "message": "Argument \"@defer(label:)\" must be a static string.",
          "locations": [
            {
              "line": 6,
              "column": 18
            }
          ]
        }
      ]
    }
  }
]
