[
  {
    "id": "4f563ca7-6315-4c69-8474-b1aebdf84c2d",
    "runId": "2026-04-25T11-11-43-961Z",
    "implId": "hot-chocolate",
    "testCaseId": "0be3846f/47d203fa/44136fa3",
    "status": "fail",
    "expected": {
      "data": {
        "__typename": "Object_ApwfNHZGC"
      }
    },
    "actual": {
      "data": null,
      "errors": [
        {
          "message": "The specified directive `experimental_disableErrorPropagation` is not supported by the current schema."
        }
      ]
    }
  },
  {
    "id": "52d0cc87-fbf6-48c1-84ab-35b5da6df738",
    "runId": "2026-04-25T11-11-43-961Z",
    "implId": "hot-chocolate",
    "testCaseId": "1ca6b2ac/70522189/44136fa3",
    "status": "fail",
    "expected": {
      "data": {
        "lj": "UruN2Q"
      }
    },
    "actual": {
      "data": null,
      "errors": [
        {
          "message": "The specified directive `experimental_disableErrorPropagation` is not supported by the current schema."
        }
      ]
    }
  },
  {
    "id": "cbce8cdd-a173-4f9c-81ae-a93a360ef811",
    "runId": "2026-04-25T11-11-43-961Z",
    "implId": "hot-chocolate",
    "testCaseId": "1ca6b2ac/9964f5db/44136fa3",
    "status": "fail",
    "expected": {
      "data": {
        "BAvi9OFQ": "UruN2Q"
      }
    },
    "actual": {
      "data": null,
      "errors": [
        {
          "message": "The specified directive `experimental_disableErrorPropagation` is not supported by the current schema."
        }
      ]
    }
  },
  {
    "id": "96f5a725-362c-4100-8832-51aa86302c56",
    "runId": "2026-04-25T11-11-43-961Z",
    "implId": "hot-chocolate",
    "testCaseId": "260aa9c0/3db04ec7/44136fa3",
    "status": "fail",
    "expected": {
      "data": {
        "lSwApAg14J": "Qqdt4w"
      }
    },
    "actual": {
      "data": null,
      "errors": [
        {
          "message": "The specified directive `experimental_disableErrorPropagation` is not supported by the current schema."
        }
      ]
    }
  },
  {
    "id": "d1764fe7-f50b-4eb2-8b0c-9fc6897ea5e4",
    "runId": "2026-04-25T11-11-43-961Z",
    "implId": "hot-chocolate",
    "testCaseId": "3275639d/e1e0f6af/bdfd558e",
    "status": "fail",
    "expected": {
      "data": {
        "__typename": "Object_Yeeu",
        "Nk": "Object_Yeeu",
        "Ke": "Object_Yeeu",
        "dGIrtw6e6D": "id"
      }
    },
    "actual": {
      "data": null,
      "errors": [
        {
          "message": "The specified directive `experimental_disableErrorPropagation` is not supported by the current schema."
        }
      ]
    }
  },
  {
    "id": "ccd0b804-ecf4-477c-88b9-eac597080827",
    "runId": "2026-04-25T11-11-43-961Z",
    "implId": "hot-chocolate",
    "testCaseId": "3275639d/e1e0f6af/fad39b65",
    "status": "fail",
    "expected": {
      "data": {
        "Ke": "Object_Yeeu",
        "dGIrtw6e6D": "id",
        "__typename": "Object_Yeeu",
        "Nk": "Object_Yeeu"
      }
    },
    "actual": {
      "data": null,
      "errors": [
        {
          "message": "The specified directive `experimental_disableErrorPropagation` is not supported by the current schema."
        }
      ]
    }
  },
  {
    "id": "633b0ac4-0866-4c4a-874a-50bdee1b4751",
    "runId": "2026-04-25T11-11-43-961Z",
    "implId": "hot-chocolate",
    "testCaseId": "38784eca/812c3555/44136fa3",
    "status": "fail",
    "expected": {
      "data": {
        "noFTUs_b": "Object_PWvnL0k",
        "__typename": "Object_PWvnL0k"
      }
    },
    "actual": {
      "data": null,
      "errors": [
        {
          "message": "The specified directive `experimental_disableErrorPropagation` is not supported by the current schema."
        }
      ]
    }
  },
  {
    "id": "41d1d666-e15d-4e67-8083-5cf2bdb2c184",
    "runId": "2026-04-25T11-11-43-961Z",
    "implId": "hot-chocolate",
    "testCaseId": "3a31b195/62221936/3d1e23d4",
    "status": "fail",
    "expected": {
      "data": {
        "zrMWeATm": "Object_E0NcK8",
        "mB0": "Object_E0NcK8"
      }
    },
    "actual": {
      "data": null,
      "errors": [
        {
          "message": "The specified directive `experimental_disableErrorPropagation` is not supported by the current schema."
        }
      ]
    }
  },
  {
    "id": "54eebf7d-c5d2-4dd7-8aae-4086e7cd2cfe",
    "runId": "2026-04-25T11-11-43-961Z",
    "implId": "hot-chocolate",
    "testCaseId": "3a31b195/62221936/87f4f246",
    "status": "fail",
    "expected": {
      "data": {
        "zrMWeATm": "Object_E0NcK8",
        "mB0": "Object_E0NcK8"
      }
    },
    "actual": {
      "data": null,
      "errors": [
        {
          "message": "The specified directive `experimental_disableErrorPropagation` is not supported by the current schema."
        }
      ]
    }
  },
  {
    "id": "a7fcbc6f-c258-4608-86c3-011395c9da43",
    "runId": "2026-04-25T11-11-43-961Z",
    "implId": "hot-chocolate",
    "testCaseId": "3a31b195/62221936/abd54625",
    "status": "fail",
    "expected": {
      "data": {
        "zrMWeATm": "Object_E0NcK8",
        "mB0": "Object_E0NcK8"
      }
    },
    "actual": {
      "data": null,
      "errors": [
        {
          "message": "The specified directive `experimental_disableErrorPropagation` is not supported by the current schema."
        }
      ]
    }
  },
  {
    "id": "921d5ddc-9649-45a1-8420-b0bbcad23780",
    "runId": "2026-04-25T11-11-43-961Z",
    "implId": "hot-chocolate",
    "testCaseId": "64d808be/daa5fec9/2552ba7b",
    "status": "fail",
    "expected": {
      "data": {
        "pNxWCT": "Object_qYPyO",
        "__typename": "Object_qYPyO",
        "lt": "Object_qYPyO"
      }
    },
    "actual": {
      "data": null,
      "errors": [
        {
          "message": "The specified directive `experimental_disableErrorPropagation` is not supported by the current schema."
        }
      ]
    }
  },
  {
    "id": "9dba814e-50c3-412c-84b0-825c2ba3d187",
    "runId": "2026-04-25T11-11-43-961Z",
    "implId": "hot-chocolate",
    "testCaseId": "751da379/a93b7a72/44136fa3",
    "status": "fail",
    "expected": {
      "data": {
        "d1jJl4ACGJ": "CG5we"
      }
    },
    "actual": {
      "data": null,
      "errors": [
        {
          "message": "The specified directive `experimental_disableErrorPropagation` is not supported by the current schema."
        }
      ]
    }
  },
  {
    "id": "d7dbc340-0ce7-4cda-8e01-e9a32d665d8f",
    "runId": "2026-04-25T11-11-43-961Z",
    "implId": "hot-chocolate",
    "testCaseId": "8ffc685b/5735547a/44136fa3",
    "status": "fail",
    "expected": {
      "data": {
        "x": "b",
        "__typename": "Object_u"
      }
    },
    "actual": {
      "data": null,
      "errors": [
        {
          "message": "The specified directive `experimental_disableErrorPropagation` is not supported by the current schema."
        }
      ]
    }
  },
  {
    "id": "8ee07fe3-f793-4bfe-8fb6-77df12c1ffea",
    "runId": "2026-04-25T11-11-43-961Z",
    "implId": "hot-chocolate",
    "testCaseId": "989abafa/a04f33bb/44136fa3",
    "status": "fail",
    "expected": {
      "data": {
        "__typename": "Object_k"
      }
    },
    "actual": {
      "data": null,
      "errors": [
        {
          "message": "The specified directive `experimental_disableErrorPropagation` is not supported by the current schema."
        }
      ]
    }
  },
  {
    "id": "4fbefe76-7ca3-4063-880b-301c5c0045b7",
    "runId": "2026-04-25T11-11-43-961Z",
    "implId": "hot-chocolate",
    "testCaseId": "9c43f4e7/55d1afce/44136fa3",
    "status": "fail",
    "expected": {
      "data": {
        "qHpki6a": "id",
        "grFOPvI": {
          "yF": "FZLXylYNy"
        },
        "snL": {
          "__typename": "Interface_t_STUB",
          "l": "VbH23o85nO"
        },
        "__typename": "Object_IlyM5C"
      }
    },
    "actual": {
      "data": null,
      "errors": [
        {
          "message": "The specified directive `experimental_disableErrorPropagation` is not supported by the current schema."
        }
      ]
    }
  },
  {
    "id": "ad6ff489-00a3-4cbc-8b29-760728a60081",
    "runId": "2026-04-25T11-11-43-961Z",
    "implId": "hot-chocolate",
    "testCaseId": "ae24e0f3/f802d4ad/44136fa3",
    "status": "fail",
    "expected": {
      "data": {
        "aZ4fK1deRM": "str",
        "__typename": "Object_K0b5ePiHN"
      }
    },
    "actual": {
      "data": null,
      "errors": [
        {
          "message": "The specified directive `experimental_disableErrorPropagation` is not supported by the current schema."
        }
      ]
    }
  },
  {
    "id": "fc3d1d63-ff5d-46f5-8f64-d239ae15b265",
    "runId": "2026-04-25T11-11-43-961Z",
    "implId": "hot-chocolate",
    "testCaseId": "c7e14b7a/610d2793/44136fa3",
    "status": "fail",
    "expected": {
      "data": {
        "__typename": "Object_A"
      }
    },
    "actual": {
      "data": null,
      "errors": [
        {
          "message": "The specified directive `experimental_disableErrorPropagation` is not supported by the current schema."
        }
      ]
    }
  },
  {
    "id": "c46cb5d5-3073-490c-8607-d4737c707a43",
    "runId": "2026-04-25T11-11-43-961Z",
    "implId": "hot-chocolate",
    "testCaseId": "ca8b9739/a10fa7b0/2db84a2d",
    "status": "fail",
    "expected": {
      "data": {
        "__typename": "Object_hEw",
        "sg2E": {
          "ni1bbI5AU": [
            "pGn",
            "pGn"
          ],
          "o8": "xBA40RkVs"
        },
        "dJczP8Cs": {
          "__typename": "Object_XlToXN8uz"
        },
        "ni1bbI5AU": [
          "pGn",
          "pGn"
        ],
        "o8": "xBA40RkVs",
        "lZ6SY": [
          "pGn",
          "pGn"
        ],
        "V3pF": [
          "pGn",
          "pGn"
        ]
      }
    },
    "actual": {
      "data": null,
      "errors": [
        {
          "message": "The specified directive `experimental_disableErrorPropagation` is not supported by the current schema."
        }
      ]
    }
  },
  {
    "id": "6ad02923-241c-4947-8228-e910dae74eb3",
    "runId": "2026-04-25T11-11-43-961Z",
    "implId": "hot-chocolate",
    "testCaseId": "ca8b9739/a10fa7b0/6e4febb4",
    "status": "fail",
    "expected": {
      "data": {
        "__typename": "Object_hEw",
        "sg2E": {
          "ni1bbI5AU": [
            "pGn",
            "pGn"
          ],
          "o8": "xBA40RkVs"
        },
        "dJczP8Cs": {
          "__typename": "Object_XlToXN8uz"
        },
        "ni1bbI5AU": [
          "pGn",
          "pGn"
        ],
        "o8": "xBA40RkVs",
        "lZ6SY": [
          "pGn",
          "pGn"
        ],
        "V3pF": [
          "pGn",
          "pGn"
        ]
      }
    },
    "actual": {
      "data": null,
      "errors": [
        {
          "message": "The specified directive `experimental_disableErrorPropagation` is not supported by the current schema."
        }
      ]
    }
  },
  {
    "id": "01db6c57-6edc-466d-8060-75a8865c3471",
    "runId": "2026-04-25T11-11-43-961Z",
    "implId": "hot-chocolate",
    "testCaseId": "d0f72165/de641c8a/44136fa3",
    "status": "fail",
    "expected": {
      "data": {
        "__typename": "Object_g",
        "wqzAC": "Object_g",
        "vec0R_Q6u": {
          "__typename": "Interface_kOFJI_STUB",
          "a0Olo1N_": {
            "__typename": "Object_g"
          }
        }
      }
    },
    "actual": {
      "data": null,
      "errors": [
        {
          "message": "The specified directive `experimental_disableErrorPropagation` is not supported by the current schema."
        }
      ]
    }
  },
  {
    "id": "bfc1fc64-f4d7-4060-8217-bdce9d96ce8d",
    "runId": "2026-04-25T11-11-43-961Z",
    "implId": "hot-chocolate",
    "testCaseId": "e0c0a435/1140b341/44136fa3",
    "status": "fail",
    "expected": {
      "data": {
        "__typename": "Object_aaghjtY"
      }
    },
    "actual": {
      "data": null,
      "errors": [
        {
          "message": "The specified directive `experimental_disableErrorPropagation` is not supported by the current schema."
        }
      ]
    }
  },
  {
    "id": "42ca442b-3acd-4bb0-87a5-cd1107578a0e",
    "runId": "2026-04-25T11-11-43-961Z",
    "implId": "hot-chocolate",
    "testCaseId": "e254fdcd/b2ce683f/27586576",
    "status": "fail",
    "expected": {
      "data": {
        "tL9uCuZ": "Y",
        "__typename": "Object_Am_AlXm",
        "hcPuv0V": {
          "__typename": "Object_Go"
        },
        "M": {
          "__typename": "Object_Go",
          "j": true
        },
        "WZx": {
          "_5NsiTeOBi": "Object_Go"
        }
      }
    },
    "actual": {
      "data": null,
      "errors": [
        {
          "message": "The specified directive `experimental_disableErrorPropagation` is not supported by the current schema."
        }
      ]
    }
  },
  {
    "id": "6e58138f-79e5-4743-8636-c1af74be3154",
    "runId": "2026-04-25T11-11-43-961Z",
    "implId": "hot-chocolate",
    "testCaseId": "e254fdcd/b2ce683f/7702f8cc",
    "status": "fail",
    "expected": {
      "data": {
        "tL9uCuZ": "Y",
        "__typename": "Object_Am_AlXm",
        "hcPuv0V": {
          "__typename": "Object_Go"
        },
        "M": {
          "__typename": "Object_Go",
          "j": true
        },
        "WZx": {
          "_5NsiTeOBi": "Object_Go"
        }
      }
    },
    "actual": {
      "data": null,
      "errors": [
        {
          "message": "The specified directive `experimental_disableErrorPropagation` is not supported by the current schema."
        }
      ]
    }
  },
  {
    "id": "6a045f09-c1cd-4fce-8e13-a6786d338822",
    "runId": "2026-04-25T11-11-43-961Z",
    "implId": "hot-chocolate",
    "testCaseId": "f48df69e/25cb01a4/44136fa3",
    "status": "fail",
    "expected": {
      "data": {
        "N": "Object_KJDYJkCZK",
        "__typename": "Object_KJDYJkCZK"
      }
    },
    "actual": {
      "data": null,
      "errors": [
        {
          "message": "The specified directive `experimental_disableErrorPropagation` is not supported by the current schema."
        }
      ]
    }
  }
]
