[
  {
    "id": "03a847a4-aa6c-4855-86f6-209fd5a1edde",
    "runId": "dda9026f-fa49-44d7-b327-49710e1cfe02",
    "implId": "graphql-dotnet",
    "testCaseId": "0565cafd/428c233b/44136fa3",
    "status": "error",
    "expected": {
      "data": {
        "jrWn": true
      }
    },
    "error": "The default value of Input Object type field 'Input_pQSaVr76.fKKsKNm' is invalid.",
    "stderr": "{\"errors\":[{\"message\":\"The default value of Input Object type field \\u0027Input_pQSaVr76.fKKsKNm\\u0027 is invalid.\"}]}"
  },
  {
    "id": "3d58c2ce-ba5a-48db-89e4-402820bb2ef8",
    "runId": "dda9026f-fa49-44d7-b327-49710e1cfe02",
    "implId": "graphql-dotnet",
    "testCaseId": "0565cafd/4cfeef10/44136fa3",
    "status": "error",
    "expected": {
      "data": {
        "__typename": "Object_bd",
        "XTh": "Object_bd"
      }
    },
    "error": "The default value of Input Object type field 'Input_pQSaVr76.fKKsKNm' is invalid.",
    "stderr": "{\"errors\":[{\"message\":\"The default value of Input Object type field \\u0027Input_pQSaVr76.fKKsKNm\\u0027 is invalid.\"}]}"
  },
  {
    "id": "4b6fa3a2-9bd6-461a-8e4e-fc817f5e78e7",
    "runId": "dda9026f-fa49-44d7-b327-49710e1cfe02",
    "implId": "graphql-dotnet",
    "testCaseId": "0565cafd/6f196a73/44136fa3",
    "status": "error",
    "expected": {
      "data": {
        "__typename": "Object_bd"
      }
    },
    "error": "The default value of Input Object type field 'Input_pQSaVr76.fKKsKNm' is invalid.",
    "stderr": "{\"errors\":[{\"message\":\"The default value of Input Object type field \\u0027Input_pQSaVr76.fKKsKNm\\u0027 is invalid.\"}]}"
  },
  {
    "id": "fc3ac56b-31cf-460e-8d60-38f3a04ad3a9",
    "runId": "dda9026f-fa49-44d7-b327-49710e1cfe02",
    "implId": "graphql-dotnet",
    "testCaseId": "0565cafd/8a20c5f6/44136fa3",
    "status": "error",
    "expected": {
      "data": {
        "HQxxb9z": [
          {
            "f8": [
              true,
              true
            ]
          },
          {
            "f8": [
              true,
              true
            ]
          }
        ],
        "J518": [
          {
            "__typename": "Interface_U61e_STUB"
          },
          {
            "__typename": "Interface_U61e_STUB"
          }
        ],
        "__typename": "Object_bd"
      }
    },
    "error": "The default value of Input Object type field 'Input_pQSaVr76.fKKsKNm' is invalid.",
    "stderr": "{\"errors\":[{\"message\":\"The default value of Input Object type field \\u0027Input_pQSaVr76.fKKsKNm\\u0027 is invalid.\"}]}"
  },
  {
    "id": "1848ba7b-5823-48b6-8970-6696cec2e7ce",
    "runId": "dda9026f-fa49-44d7-b327-49710e1cfe02",
    "implId": "graphql-dotnet",
    "testCaseId": "0565cafd/9f5bb655/44136fa3",
    "status": "error",
    "expected": {
      "data": {
        "cDAO089m0": "Object_bd"
      }
    },
    "error": "The default value of Input Object type field 'Input_pQSaVr76.fKKsKNm' is invalid.",
    "stderr": "{\"errors\":[{\"message\":\"The default value of Input Object type field \\u0027Input_pQSaVr76.fKKsKNm\\u0027 is invalid.\"}]}"
  },
  {
    "id": "154c18d2-0f1b-43f1-8f9f-4f8480cc2634",
    "runId": "dda9026f-fa49-44d7-b327-49710e1cfe02",
    "implId": "graphql-dotnet",
    "testCaseId": "0565cafd/cd9f770b/44136fa3",
    "status": "error",
    "expected": {
      "data": {
        "__typename": "Object_bd",
        "NaTj": "Object_bd"
      }
    },
    "error": "The default value of Input Object type field 'Input_pQSaVr76.fKKsKNm' is invalid.",
    "stderr": "{\"errors\":[{\"message\":\"The default value of Input Object type field \\u0027Input_pQSaVr76.fKKsKNm\\u0027 is invalid.\"}]}"
  },
  {
    "id": "27e97c59-fa0d-412c-814e-d0b53bdfbd0b",
    "runId": "dda9026f-fa49-44d7-b327-49710e1cfe02",
    "implId": "graphql-dotnet",
    "testCaseId": "0565cafd/dce9e68f/44136fa3",
    "status": "error",
    "expected": {
      "data": {
        "__typename": "Object_bd"
      }
    },
    "error": "The default value of Input Object type field 'Input_pQSaVr76.fKKsKNm' is invalid.",
    "stderr": "{\"errors\":[{\"message\":\"The default value of Input Object type field \\u0027Input_pQSaVr76.fKKsKNm\\u0027 is invalid.\"}]}"
  },
  {
    "id": "308228f6-9b08-44ab-887d-353429527e5d",
    "runId": "dda9026f-fa49-44d7-b327-49710e1cfe02",
    "implId": "graphql-dotnet",
    "testCaseId": "0565cafd/e841846b/44136fa3",
    "status": "error",
    "expected": {
      "data": {
        "__typename": "Object_bd",
        "j": [
          {
            "__typename": "Interface_U61e_STUB"
          },
          {
            "__typename": "Interface_U61e_STUB"
          }
        ],
        "jrWn": true,
        "ikBVofJQ": true
      }
    },
    "error": "The default value of Input Object type field 'Input_pQSaVr76.fKKsKNm' is invalid.",
    "stderr": "{\"errors\":[{\"message\":\"The default value of Input Object type field \\u0027Input_pQSaVr76.fKKsKNm\\u0027 is invalid.\"}]}"
  },
  {
    "id": "29aaceb4-b732-4d4a-854c-728cefc262c9",
    "runId": "dda9026f-fa49-44d7-b327-49710e1cfe02",
    "implId": "graphql-dotnet",
    "testCaseId": "0565cafd/e841846b/6dfb7769",
    "status": "error",
    "expected": {
      "data": {
        "__typename": "Object_bd",
        "j": [
          {
            "__typename": "Interface_U61e_STUB"
          },
          {
            "__typename": "Interface_U61e_STUB"
          }
        ],
        "jrWn": true,
        "ikBVofJQ": true
      }
    },
    "error": "The default value of Input Object type field 'Input_pQSaVr76.fKKsKNm' is invalid.",
    "stderr": "{\"errors\":[{\"message\":\"The default value of Input Object type field \\u0027Input_pQSaVr76.fKKsKNm\\u0027 is invalid.\"}]}"
  },
  {
    "id": "6f586c4f-43df-48c6-8cbd-c6897414a9b5",
    "runId": "dda9026f-fa49-44d7-b327-49710e1cfe02",
    "implId": "graphql-dotnet",
    "testCaseId": "0565cafd/e841846b/852980e1",
    "status": "error",
    "expected": {
      "data": {
        "__typename": "Object_bd",
        "j": [
          {
            "__typename": "Interface_U61e_STUB"
          },
          {
            "__typename": "Interface_U61e_STUB"
          }
        ],
        "jrWn": true,
        "ikBVofJQ": true
      }
    },
    "error": "The default value of Input Object type field 'Input_pQSaVr76.fKKsKNm' is invalid.",
    "stderr": "{\"errors\":[{\"message\":\"The default value of Input Object type field \\u0027Input_pQSaVr76.fKKsKNm\\u0027 is invalid.\"}]}"
  }
]
