[
  {
    "id": "69cca727-02b7-4e1f-81e8-8a47a80c6005",
    "runId": "9a1d5292-4600-4611-8f72-f3db00a2d364",
    "implId": "async-graphql",
    "testCaseId": "034907e7/08233559/724a47a1",
    "status": "fail",
    "expected": {
      "data": {
        "__typename": "Object_jGekrLP4U",
        "c5GCEDZ": "id",
        "n_kMSMjl": "id"
      }
    },
    "actual": {
      "data": {
        "__typename": "Object_jGekrLP4U",
        "n_kMSMjl": "id"
      }
    }
  },
  {
    "id": "98a0ca2d-8b3a-49dd-8baa-07e9f67d933d",
    "runId": "9a1d5292-4600-4611-8f72-f3db00a2d364",
    "implId": "async-graphql",
    "testCaseId": "034907e7/09274984/e1d651ba",
    "status": "fail",
    "expected": {
      "data": {
        "Uf": "Object_jGekrLP4U",
        "__typename": "Object_jGekrLP4U",
        "a": "id"
      }
    },
    "actual": {
      "data": {}
    }
  },
  {
    "id": "2668fa9a-5fcc-4479-8a35-e74936f5e0cc",
    "runId": "9a1d5292-4600-4611-8f72-f3db00a2d364",
    "implId": "async-graphql",
    "testCaseId": "034907e7/09274984/f00482f3",
    "status": "fail",
    "expected": {
      "data": {
        "Uf": "Object_jGekrLP4U",
        "__typename": "Object_jGekrLP4U",
        "a": "id"
      }
    },
    "actual": {
      "data": {}
    }
  },
  {
    "id": "f9bce574-51f2-4348-8cee-5d97760d6dd1",
    "runId": "9a1d5292-4600-4611-8f72-f3db00a2d364",
    "implId": "async-graphql",
    "testCaseId": "034907e7/5f421a36/44136fa3",
    "status": "fail",
    "expected": {
      "data": {
        "lPfrwoN": "Object_jGekrLP4U"
      }
    },
    "actual": {
      "data": {}
    }
  },
  {
    "id": "ce4d58dc-f1e1-4f3f-8000-300a1ad580b5",
    "runId": "9a1d5292-4600-4611-8f72-f3db00a2d364",
    "implId": "async-graphql",
    "testCaseId": "034907e7/7990cc4f/44136fa3",
    "status": "fail",
    "expected": {
      "data": {
        "dQ6WtE34": true,
        "__typename": "Object_jGekrLP4U"
      }
    },
    "actual": {
      "data": {
        "dQ6WtE34": true
      }
    }
  },
  {
    "id": "38f6ba1b-3b2f-4088-8d31-7cd1af3d41f1",
    "runId": "9a1d5292-4600-4611-8f72-f3db00a2d364",
    "implId": "async-graphql",
    "testCaseId": "034907e7/93c616f0/44136fa3",
    "status": "fail",
    "expected": {
      "data": {
        "__typename": "Object_jGekrLP4U",
        "c5GCEDZ": "id"
      }
    },
    "actual": {
      "data": {
        "c5GCEDZ": "id"
      }
    }
  },
  {
    "id": "49ee8e54-3368-448b-8a78-f92a51a9f516",
    "runId": "9a1d5292-4600-4611-8f72-f3db00a2d364",
    "implId": "async-graphql",
    "testCaseId": "034907e7/ea93ad2f/44136fa3",
    "status": "fail",
    "expected": {
      "data": {
        "__typename": "Object_jGekrLP4U",
        "L": "Object_jGekrLP4U",
        "a": "id"
      }
    },
    "actual": {
      "data": {
        "a": "id"
      }
    }
  },
  {
    "id": "4479d33e-d75c-4eba-817d-7ee00df743d4",
    "runId": "9a1d5292-4600-4611-8f72-f3db00a2d364",
    "implId": "async-graphql",
    "testCaseId": "034907e7/f08f01a6/44136fa3",
    "status": "fail",
    "expected": {
      "data": {
        "y9Sef": "Object_jGekrLP4U",
        "__typename": "Object_jGekrLP4U"
      }
    },
    "actual": {
      "data": {}
    }
  },
  {
    "id": "2a3737ce-47df-484a-8d2e-83a0c1377559",
    "runId": "9a1d5292-4600-4611-8f72-f3db00a2d364",
    "implId": "async-graphql",
    "testCaseId": "03573f34/0bddac9f/44136fa3",
    "status": "fail",
    "expected": {
      "data": {
        "__typename": "Object_lpJFn"
      }
    },
    "actual": {
      "data": {}
    }
  },
  {
    "id": "3b1cfa8e-8e26-4aec-869e-9d117dd37717",
    "runId": "9a1d5292-4600-4611-8f72-f3db00a2d364",
    "implId": "async-graphql",
    "testCaseId": "03573f34/1a4227c3/44136fa3",
    "status": "fail",
    "expected": {
      "data": {
        "__typename": "Object_lpJFn",
        "xunqtFHE": "Object_lpJFn",
        "x4cbu6cZ": {
          "__typename": "Interface_j4AUR_STUB",
          "R5Ldbv_": {
            "gf": true
          },
          "wvF": "Interface_j4AUR_STUB",
          "deWZL": "XtCw_c",
          "zhKE": {
            "ITX": "Interface_D_STUB"
          }
        },
        "msiDCGEKr": "Object_lpJFn"
      }
    },
    "actual": {
      "data": {
        "__typename": "Object_lpJFn",
        "x4cbu6cZ": {
          "R5Ldbv_": {
            "gf": true
          },
          "__typename": "Interface_j4AUR_STUB",
          "deWZL": "XtCw_c",
          "wvF": "Interface_j4AUR_STUB",
          "zhKE": {
            "ITX": "Interface_D_STUB"
          }
        },
        "xunqtFHE": "Object_lpJFn"
      }
    }
  }
]
