[
  {
    "id": "c5787f42-bb89-4d62-85a4-a7cf2976e9b3",
    "runId": "fcc9f740-e8c5-42a2-9ed0-8c4700282662",
    "implId": "lacinia",
    "testCaseId": "034907e7/08233559/724a47a1",
    "status": "error",
    "expected": {
      "data": {
        "__typename": "Object_jGekrLP4U",
        "c5GCEDZ": "id",
        "n_kMSMjl": "id"
      }
    },
    "error": "Failed to parse GraphQL schema.",
    "stderr": "{\"errors\":[{\"message\":\"Failed to parse GraphQL schema.\"}]}"
  },
  {
    "id": "cd136fcd-d043-4d41-88b8-ecbff903c76f",
    "runId": "fcc9f740-e8c5-42a2-9ed0-8c4700282662",
    "implId": "lacinia",
    "testCaseId": "034907e7/09274984/e1d651ba",
    "status": "error",
    "expected": {
      "data": {
        "Uf": "Object_jGekrLP4U",
        "__typename": "Object_jGekrLP4U",
        "a": "id"
      }
    },
    "error": "Failed to parse GraphQL schema.",
    "stderr": "{\"errors\":[{\"message\":\"Failed to parse GraphQL schema.\"}]}"
  },
  {
    "id": "c140f6f9-0ede-4dea-8e41-9b23547a0c26",
    "runId": "fcc9f740-e8c5-42a2-9ed0-8c4700282662",
    "implId": "lacinia",
    "testCaseId": "034907e7/09274984/f00482f3",
    "status": "error",
    "expected": {
      "data": {
        "Uf": "Object_jGekrLP4U",
        "__typename": "Object_jGekrLP4U",
        "a": "id"
      }
    },
    "error": "Failed to parse GraphQL schema.",
    "stderr": "{\"errors\":[{\"message\":\"Failed to parse GraphQL schema.\"}]}"
  },
  {
    "id": "edd2e3cb-3c51-4c44-8e51-b45a13dfc8cc",
    "runId": "fcc9f740-e8c5-42a2-9ed0-8c4700282662",
    "implId": "lacinia",
    "testCaseId": "034907e7/4f583e2d/44136fa3",
    "status": "error",
    "expected": {
      "data": {
        "c5GCEDZ": "id"
      }
    },
    "error": "Failed to parse GraphQL schema.",
    "stderr": "{\"errors\":[{\"message\":\"Failed to parse GraphQL schema.\"}]}"
  },
  {
    "id": "beea161e-e592-4324-8fc9-ca78f53d88ba",
    "runId": "fcc9f740-e8c5-42a2-9ed0-8c4700282662",
    "implId": "lacinia",
    "testCaseId": "034907e7/5f421a36/44136fa3",
    "status": "error",
    "expected": {
      "data": {
        "lPfrwoN": "Object_jGekrLP4U"
      }
    },
    "error": "Failed to parse GraphQL schema.",
    "stderr": "{\"errors\":[{\"message\":\"Failed to parse GraphQL schema.\"}]}"
  },
  {
    "id": "e65c225c-9f9c-4433-8943-e14543fc27a5",
    "runId": "fcc9f740-e8c5-42a2-9ed0-8c4700282662",
    "implId": "lacinia",
    "testCaseId": "034907e7/7990cc4f/44136fa3",
    "status": "error",
    "expected": {
      "data": {
        "dQ6WtE34": true,
        "__typename": "Object_jGekrLP4U"
      }
    },
    "error": "Failed to parse GraphQL schema.",
    "stderr": "{\"errors\":[{\"message\":\"Failed to parse GraphQL schema.\"}]}"
  },
  {
    "id": "e1c22eed-8d3e-488a-8054-35a858b75992",
    "runId": "fcc9f740-e8c5-42a2-9ed0-8c4700282662",
    "implId": "lacinia",
    "testCaseId": "034907e7/93c616f0/44136fa3",
    "status": "error",
    "expected": {
      "data": {
        "__typename": "Object_jGekrLP4U",
        "c5GCEDZ": "id"
      }
    },
    "error": "Failed to parse GraphQL schema.",
    "stderr": "{\"errors\":[{\"message\":\"Failed to parse GraphQL schema.\"}]}"
  },
  {
    "id": "619d7289-6e2a-4639-8d6e-c08d4e306b48",
    "runId": "fcc9f740-e8c5-42a2-9ed0-8c4700282662",
    "implId": "lacinia",
    "testCaseId": "034907e7/caf52a10/44136fa3",
    "status": "error",
    "expected": {
      "data": {
        "c5GCEDZ": "id"
      }
    },
    "error": "Failed to parse GraphQL schema.",
    "stderr": "{\"errors\":[{\"message\":\"Failed to parse GraphQL schema.\"}]}"
  },
  {
    "id": "a9203917-bd8a-4844-8d12-b9ebbb004ef3",
    "runId": "fcc9f740-e8c5-42a2-9ed0-8c4700282662",
    "implId": "lacinia",
    "testCaseId": "034907e7/d42e84e4/44136fa3",
    "status": "error",
    "expected": {
      "data": {
        "c5GCEDZ": "id"
      }
    },
    "error": "Failed to parse GraphQL schema.",
    "stderr": "{\"errors\":[{\"message\":\"Failed to parse GraphQL schema.\"}]}"
  },
  {
    "id": "6634906f-431d-4715-8423-5d6cfb5f49f9",
    "runId": "fcc9f740-e8c5-42a2-9ed0-8c4700282662",
    "implId": "lacinia",
    "testCaseId": "034907e7/ea93ad2f/44136fa3",
    "status": "error",
    "expected": {
      "data": {
        "__typename": "Object_jGekrLP4U",
        "L": "Object_jGekrLP4U",
        "a": "id"
      }
    },
    "error": "Failed to parse GraphQL schema.",
    "stderr": "{\"errors\":[{\"message\":\"Failed to parse GraphQL schema.\"}]}"
  }
]
